pdpipe/__init__.py
pdpipe/_version.py
pdpipe/basic_stages.py
pdpipe/cfg.py
pdpipe/col_generation.py
pdpipe/cond.py
pdpipe/core.py
pdpipe/cq.py
pdpipe/exceptions.py
pdpipe/fly.py
pdpipe/lbl.py
pdpipe/nltk_stages.py
pdpipe/pdp_types.py
pdpipe/rq.py
pdpipe/run_time_parameters.py
pdpipe/shared.py
pdpipe/skintegrate.py
pdpipe/sklearn_stages.py
pdpipe/text_stages.py
pdpipe/util.py
pdpipe/version.info
pdpipe/wrappers.py
pdpipe/df/__init__.py
pdpipe/df/bound_column_potential.py
pdpipe/df/df.py
pdpipe/df/df_transformer.py
pdpipe/df/func_lists.py
pdpipe/df/series_from_df.py
pdpipe-1.1.0.dist-info/licenses/LICENSE
pdpipe-1.1.0.dist-info/METADATA
pdpipe-1.1.0.dist-info/WHEEL
pdpipe-1.1.0.dist-info/top_level.txt
pdpipe-1.1.0.dist-info/RECORD
