Metadata-Version: 2.4
Name: pdpipe
Version: 1.1.0
Summary: Easy pipelines for pandas.
Author-email: Shay Palachy Affek <shay.palachy@gmail.com>
License: MIT License
Project-URL: Source, https://pdpipe.readthedocs.io/en/latest/
Keywords: pdpipe,pandas,pandas pipeline,pipeline,dataframe,data science,machine learning,python,utilities,utils
Classifier: Development Status :: 4 - Beta
Classifier: Intended Audience :: Developers
Classifier: License :: OSI Approved :: MIT License
Classifier: Programming Language :: Python
Classifier: Programming Language :: Python :: 3 :: Only
Classifier: Programming Language :: Python :: 3.9
Classifier: Programming Language :: Python :: 3.10
Classifier: Programming Language :: Python :: 3.11
Classifier: Programming Language :: Python :: 3.12
Classifier: Programming Language :: Python :: 3.13
Classifier: Topic :: Other/Nonlisted Topic
Classifier: Topic :: Software Development :: Libraries
Classifier: Topic :: Software Development :: Libraries :: Python Modules
Classifier: Topic :: Utilities
License-File: LICENSE
Requires-Dist: pandas>=2.0.0
Requires-Dist: sortedcontainers
Requires-Dist: tqdm
Requires-Dist: strct
Requires-Dist: skutil>=0.0.15
Requires-Dist: birch>=0.0.34
Provides-Extra: sklearn
Requires-Dist: scikit-learn; extra == "sklearn"
Provides-Extra: nltk
Requires-Dist: nltk; extra == "nltk"
Dynamic: license-file
